{
  "annotations": {
    "list": [
      {
        "builtIn": 1,
        "datasource": {
          "type": "grafana",
          "uid": "-- Grafana --"
        },
        "enable": true,
        "hide": true,
        "iconColor": "rgba(0, 211, 255, 1)",
        "name": "Annotations & Alerts",
        "type": "dashboard"
      }
    ]
  },
  "editable": true,
  "fiscalYearStartMonth": 0,
  "graphTooltip": 0,
  "id": null,
  "links": [],
  "liveNow": false,
  "panels": [
    {
      "datasource": {
        "type": "prometheus"
      },
      "fieldConfig": {
        "defaults": {
          "color": {
            "mode": "thresholds"
          },
          "custom": {
            "align": "auto",
            "displayMode": "auto",
            "inspect": false
          },
          "mappings": [],
          "thresholds": {
            "mode": "absolute",
            "steps": [
              {
                "color": "green",
                "value": null
              },
              {
                "color": "red",
                "value": 80
              }
            ]
          }
        },
        "overrides": []
      },
      "gridPos": {
        "h": 8,
        "w": 24,
        "x": 0,
        "y": 0
      },
      "id": 1,
      "options": {
        "showHeader": true
      },
      "pluginVersion": "8.5.2",
      "targets": [
        {
          "datasource": {
            "type": "prometheus"
          },
          "editorMode": "code",
          "expr": "sort_desc(sum by (customer_id) (rate(metald_metrics_collected_total{customer_id=~\"$customer_id\"}[$__rate_interval]) * 60))",
          "format": "table",
          "interval": "",
          "legendFormat": "__auto",
          "range": true,
          "refId": "A"
        }
      ],
      "title": "Customer Metrics Collection Rate (per minute)",
      "transformations": [
        {
          "id": "organize",
          "options": {
            "excludeByName": {
              "Time": true
            },
            "indexByName": {},
            "renameByName": {
              "Value": "Metrics/min",
              "customer_id": "Customer ID"
            }
          }
        }
      ],
      "type": "table"
    },
    {
      "datasource": {
        "type": "prometheus"
      },
      "fieldConfig": {
        "defaults": {
          "color": {
            "mode": "palette-classic"
          },
          "custom": {
            "axisLabel": "",
            "axisPlacement": "auto",
            "barAlignment": 0,
            "drawStyle": "line",
            "fillOpacity": 10,
            "gradientMode": "none",
            "hideFrom": {
              "legend": false,
              "tooltip": false,
              "vis": false
            },
            "lineInterpolation": "linear",
            "lineWidth": 1,
            "pointSize": 5,
            "scaleDistribution": {
              "type": "linear"
            },
            "showPoints": "never",
            "spanNulls": false,
            "stacking": {
              "group": "A",
              "mode": "none"
            },
            "thresholdsStyle": {
              "mode": "off"
            }
          },
          "mappings": [],
          "thresholds": {
            "mode": "absolute",
            "steps": [
              {
                "color": "green",
                "value": null
              },
              {
                "color": "red",
                "value": 80
              }
            ]
          },
          "unit": "reqps"
        },
        "overrides": []
      },
      "gridPos": {
        "h": 8,
        "w": 12,
        "x": 0,
        "y": 8
      },
      "id": 2,
      "options": {
        "legend": {
          "calcs": [],
          "displayMode": "list",
          "placement": "bottom"
        },
        "tooltip": {
          "mode": "single",
          "sort": "none"
        }
      },
      "targets": [
        {
          "datasource": {
            "type": "prometheus"
          },
          "editorMode": "code",
          "expr": "sum by (customer_id) (rate(metald_billing_batches_sent_total{customer_id=~\"$customer_id\"}[$__rate_interval]))",
          "interval": "",
          "legendFormat": "{{customer_id}}",
          "range": true,
          "refId": "A"
        }
      ],
      "title": "Billing Batch Transmission by Customer",
      "type": "timeseries"
    },
    {
      "datasource": {
        "type": "prometheus"
      },
      "fieldConfig": {
        "defaults": {
          "color": {
            "mode": "palette-classic"
          },
          "custom": {
            "axisLabel": "",
            "axisPlacement": "auto",
            "barAlignment": 0,
            "drawStyle": "line",
            "fillOpacity": 10,
            "gradientMode": "none",
            "hideFrom": {
              "legend": false,
              "tooltip": false,
              "vis": false
            },
            "lineInterpolation": "linear",
            "lineWidth": 1,
            "pointSize": 5,
            "scaleDistribution": {
              "type": "linear"
            },
            "showPoints": "never",
            "spanNulls": false,
            "stacking": {
              "group": "A",
              "mode": "normal"
            },
            "thresholdsStyle": {
              "mode": "off"
            }
          },
          "mappings": [],
          "thresholds": {
            "mode": "absolute",
            "steps": [
              {
                "color": "green",
                "value": null
              },
              {
                "color": "red",
                "value": 80
              }
            ]
          },
          "unit": "reqps"
        },
        "overrides": []
      },
      "gridPos": {
        "h": 8,
        "w": 12,
        "x": 12,
        "y": 8
      },
      "id": 3,
      "options": {
        "legend": {
          "calcs": [],
          "displayMode": "list",
          "placement": "bottom"
        },
        "tooltip": {
          "mode": "single",
          "sort": "none"
        }
      },
      "targets": [
        {
          "datasource": {
            "type": "prometheus"
          },
          "editorMode": "code",
          "expr": "sum by (customer_id) (rate(unkey_metald_vm_create_requests_total{customer_id=~\"$customer_id\"}[$__rate_interval]))",
          "interval": "",
          "legendFormat": "Create - {{customer_id}}",
          "range": true,
          "refId": "A"
        },
        {
          "datasource": {
            "type": "prometheus"
          },
          "editorMode": "code",
          "expr": "sum by (customer_id) (rate(unkey_metald_vm_boot_requests_total{customer_id=~\"$customer_id\"}[$__rate_interval]))",
          "interval": "",
          "legendFormat": "Boot - {{customer_id}}",
          "range": true,
          "refId": "B"
        },
        {
          "datasource": {
            "type": "prometheus"
          },
          "editorMode": "code",
          "expr": "sum by (customer_id) (rate(unkey_metald_vm_delete_requests_total{customer_id=~\"$customer_id\"}[$__rate_interval]))",
          "interval": "",
          "legendFormat": "Delete - {{customer_id}}",
          "range": true,
          "refId": "C"
        }
      ],
      "title": "VM Operations by Customer",
      "type": "timeseries"
    },
    {
      "datasource": {
        "type": "prometheus"
      },
      "fieldConfig": {
        "defaults": {
          "color": {
            "mode": "thresholds"
          },
          "custom": {
            "align": "auto",
            "displayMode": "auto",
            "inspect": false
          },
          "mappings": [],
          "thresholds": {
            "mode": "absolute",
            "steps": [
              {
                "color": "green",
                "value": null
              },
              {
                "color": "yellow",
                "value": 5
              },
              {
                "color": "red",
                "value": 10
              }
            ]
          }
        },
        "overrides": []
      },
      "gridPos": {
        "h": 8,
        "w": 12,
        "x": 0,
        "y": 16
      },
      "id": 4,
      "options": {
        "showHeader": true
      },
      "pluginVersion": "8.5.2",
      "targets": [
        {
          "datasource": {
            "type": "prometheus"
          },
          "editorMode": "code",
          "expr": "sort_desc(sum by (customer_id) (rate(unkey_metald_vm_create_failures_total{customer_id=~\"$customer_id\"}[$__rate_interval]) * 60))",
          "format": "table",
          "interval": "",
          "legendFormat": "__auto",
          "range": true,
          "refId": "A"
        }
      ],
      "title": "Customer Failure Rates (per minute)",
      "transformations": [
        {
          "id": "organize",
          "options": {
            "excludeByName": {
              "Time": true
            },
            "indexByName": {},
            "renameByName": {
              "Value": "Failures/min",
              "customer_id": "Customer ID"
            }
          }
        }
      ],
      "type": "table"
    },
    {
      "datasource": {
        "type": "prometheus"
      },
      "fieldConfig": {
        "defaults": {
          "color": {
            "mode": "palette-classic"
          },
          "custom": {
            "axisLabel": "",
            "axisPlacement": "auto",
            "barAlignment": 0,
            "drawStyle": "line",
            "fillOpacity": 10,
            "gradientMode": "none",
            "hideFrom": {
              "legend": false,
              "tooltip": false,
              "vis": false
            },
            "lineInterpolation": "linear",
            "lineWidth": 1,
            "pointSize": 5,
            "scaleDistribution": {
              "type": "linear"
            },
            "showPoints": "never",
            "spanNulls": false,
            "stacking": {
              "group": "A",
              "mode": "none"
            },
            "thresholdsStyle": {
              "mode": "off"
            }
          },
          "mappings": [],
          "thresholds": {
            "mode": "absolute",
            "steps": [
              {
                "color": "green",
                "value": null
              },
              {
                "color": "red",
                "value": 80
              }
            ]
          },
          "unit": "s"
        },
        "overrides": []
      },
      "gridPos": {
        "h": 8,
        "w": 12,
        "x": 12,
        "y": 16
      },
      "id": 5,
      "options": {
        "legend": {
          "calcs": [],
          "displayMode": "list",
          "placement": "bottom"
        },
        "tooltip": {
          "mode": "single",
          "sort": "none"
        }
      },
      "targets": [
        {
          "datasource": {
            "type": "prometheus"
          },
          "editorMode": "code",
          "expr": "histogram_quantile(0.95, sum by (customer_id, le) (rate(metald_billing_batch_send_duration_seconds_bucket{customer_id=~\"$customer_id\"}[$__rate_interval])))",
          "interval": "",
          "legendFormat": "95th percentile - {{customer_id}}",
          "range": true,
          "refId": "A"
        },
        {
          "datasource": {
            "type": "prometheus"
          },
          "editorMode": "code",
          "expr": "histogram_quantile(0.50, sum by (customer_id, le) (rate(metald_billing_batch_send_duration_seconds_bucket{customer_id=~\"$customer_id\"}[$__rate_interval])))",
          "interval": "",
          "legendFormat": "50th percentile - {{customer_id}}",
          "range": true,
          "refId": "B"
        }
      ],
      "title": "Billing Duration by Customer",
      "type": "timeseries"
    }
  ],
  "refresh": "5s",
  "schemaVersion": 36,
  "style": "dark",
  "tags": ["metald", "billing", "multi-tenant", "customer"],
  "templating": {
    "list": [
      {
        "current": {
          "selected": false,
          "text": "All",
          "value": "$__all"
        },
        "datasource": {
          "type": "prometheus"
        },
        "definition": "label_values(metald_billing_batches_sent_total, customer_id)",
        "hide": 0,
        "includeAll": true,
        "label": "Customer ID",
        "multi": true,
        "name": "customer_id",
        "options": [],
        "query": {
          "query": "label_values(metald_billing_batches_sent_total, customer_id)",
          "refId": "StandardVariableQuery"
        },
        "refresh": 1,
        "regex": "",
        "skipUrlSync": false,
        "sort": 0,
        "type": "query"
      }
    ]
  },
  "time": {
    "from": "now-15m",
    "to": "now"
  },
  "timepicker": {},
  "timezone": "",
  "title": "Metald Multi-Tenant Billing & Usage",
  "uid": "metald-multi-tenant-billing",
  "version": 1,
  "weekStart": ""
}
